qmenta/lint/__init__.py
qmenta/lint/lint.py
qmenta_lint-0.10.2.dist-info/METADATA
qmenta_lint-0.10.2.dist-info/WHEEL
qmenta_lint-0.10.2.dist-info/entry_points.txt
qmenta_lint-0.10.2.dist-info/top_level.txt
qmenta_lint-0.10.2.dist-info/RECORD
